exacb/__init__.py
exacb/cli.py
exacb/env.py
exacb/metadata.py
exacb/record.py
exacb/result.py
exacb-0.0.7.dist-info/METADATA
exacb-0.0.7.dist-info/WHEEL
exacb-0.0.7.dist-info/entry_points.txt
exacb-0.0.7.dist-info/RECORD
