Metadata-Version: 2.1
Name: exacb
Version: 0.0.7
Summary: A helper script for the exacb project
Project-URL: Documentation, https://gitlab.jsc.fz-juelich.de/exacb/exacb
Project-URL: Issues, https://gitlab.jsc.fz-juelich.de/exacb/exacb
Project-URL: Source, https://gitlab.jsc.fz-juelich.de/exacb/exacb
Author-email: Jayesh Badwaik <j.badwaik@fz-juelich.de>
License-Expression: Apache-2.0
Requires-Dist: semver
